turtles/__init__.py
turtles/_utils.py
turtles/plotting/__init__.py
turtles/plotting/_plotting.py
turtles/preprocess/__init__.py
turtles/preprocess/_transform.py
turtles/stats/__init__.py
turtles/stats/_stats.py
turtles/stats/glms/__init__.py
turtles/stats/glms/_base.py
turtles/stats/glms/_logreg.py
turtles/stats/glms/_mlr.py
turtles/stats/glms/_poisson.py
turtles/stats/glms/_warnings.py
turtles_glms-1.0.1.dist-info/licenses/LICENSE
turtles_glms-1.0.1.dist-info/METADATA
turtles_glms-1.0.1.dist-info/WHEEL
turtles_glms-1.0.1.dist-info/top_level.txt
turtles_glms-1.0.1.dist-info/RECORD
