Metadata-Version: 2.4
Name: turtles-glms
Version: 1.0.1
Summary: GLMs in Python.
Author-email: Adam Motzel <motzel.adam@gmail.com>
Project-URL: Homepage, https://github.com/adammotzel/pyglms
Project-URL: Issues, https://github.com/adammotzel/pyglms/issues
Classifier: Programming Language :: Python :: 3.10
Classifier: Programming Language :: Python :: 3.11
Classifier: Programming Language :: Python :: 3.12
Classifier: Programming Language :: Python :: 3.13
Requires-Python: >=3.10
License-File: LICENSE
Requires-Dist: numpy>=2.0.2
Requires-Dist: pandas>=2.2.3
Requires-Dist: scipy>=1.13.1
Requires-Dist: matplotlib>=3.9.4
Provides-Extra: dev
Requires-Dist: pytest>=8.3.4; extra == "dev"
Requires-Dist: pytest-cov>=6.2.1; extra == "dev"
Requires-Dist: scikit-learn>=1.6.1; extra == "dev"
Requires-Dist: statsmodels>=0.14.4; extra == "dev"
Requires-Dist: ipykernel>=6.29.5; extra == "dev"
Requires-Dist: pre-commit>=4.5.0; extra == "dev"
Dynamic: license-file
